LICENSE
MANIFEST.in
README.md
pyproject.toml
setup.py
multiqc/.DS_Store
multiqc/__init__.py
multiqc/__main__.py
multiqc/base_module.py
multiqc/config.py
multiqc/config_defaults.yaml
multiqc/interactive.py
multiqc/multiqc.py
multiqc/multiqc_report.html
multiqc/py.typed
multiqc/report.py
multiqc/search_patterns.yaml
multiqc/types.py
multiqc/validation.py
multiqc/__pycache__/__init__.cpython-311.pyc
multiqc/__pycache__/__init__.cpython-312.pyc
multiqc/__pycache__/__init__.cpython-313.pyc
multiqc/__pycache__/__init__.cpython-38.pyc
multiqc/__pycache__/__init__.cpython-39.pyc
multiqc/__pycache__/__main__.cpython-311.pyc
multiqc/__pycache__/__main__.cpython-312.pyc
multiqc/__pycache__/__main__.cpython-313.pyc
multiqc/__pycache__/__main__.cpython-38.pyc
multiqc/__pycache__/__main__.cpython-39.pyc
multiqc/__pycache__/base_module.cpython-311.pyc
multiqc/__pycache__/base_module.cpython-312.pyc
multiqc/__pycache__/base_module.cpython-313.pyc
multiqc/__pycache__/base_module.cpython-38.pyc
multiqc/__pycache__/base_module.cpython-39.pyc
multiqc/__pycache__/config.cpython-311.pyc
multiqc/__pycache__/config.cpython-312.pyc
multiqc/__pycache__/config.cpython-313.pyc
multiqc/__pycache__/config.cpython-38.pyc
multiqc/__pycache__/config.cpython-39.pyc
multiqc/__pycache__/interactive.cpython-311.pyc
multiqc/__pycache__/interactive.cpython-312.pyc
multiqc/__pycache__/interactive.cpython-313.pyc
multiqc/__pycache__/interactive.cpython-38.pyc
multiqc/__pycache__/interactive.cpython-39.pyc
multiqc/__pycache__/multiqc.cpython-311.pyc
multiqc/__pycache__/multiqc.cpython-312.pyc
multiqc/__pycache__/multiqc.cpython-313.pyc
multiqc/__pycache__/multiqc.cpython-38.pyc
multiqc/__pycache__/multiqc.cpython-39.pyc
multiqc/__pycache__/report.cpython-311.pyc
multiqc/__pycache__/report.cpython-312.pyc
multiqc/__pycache__/report.cpython-313.pyc
multiqc/__pycache__/report.cpython-38.pyc
multiqc/__pycache__/report.cpython-39.pyc
multiqc/__pycache__/types.cpython-312.pyc
multiqc_vlad.egg-info/PKG-INFO
multiqc_vlad.egg-info/SOURCES.txt
multiqc_vlad.egg-info/dependency_links.txt
multiqc_vlad.egg-info/entry_points.txt
multiqc_vlad.egg-info/requires.txt
multiqc_vlad.egg-info/top_level.txt
