Metadata-Version: 2.1
Name: multiqc-vlad
Version: 1.30.dev20250821143134
Summary: Create aggregate bioinformatics analysis reports across many samples and tools
Author-email: Phil Ewels <phil.ewels@seqera.io>, Vlad Savelyev <vladislav.savelyev@seqera.io>
License:                     GNU GENERAL PUBLIC LICENSE
Project-URL: Homepage, https://multiqc.info
Project-URL: Repository, https://github.com/MultiQC/MultiQC
Project-URL: Issues, https://github.com/MultiQC/MultiQC/issues
Project-URL: Documentation, https://docs.seqera.io/multiqc
Project-URL: Changelog, https://github.com/MultiQC/MultiQC/blob/main/CHANGELOG.md
Keywords: bioinformatics,biology,sequencing,NGS,next generation sequencing,quality control
Classifier: Development Status :: 5 - Production/Stable
Classifier: Environment :: Console
Classifier: Environment :: Web Environment
Classifier: Intended Audience :: Science/Research
Classifier: License :: OSI Approved :: GNU General Public License v3 (GPLv3)
Classifier: Natural Language :: English
Classifier: Operating System :: MacOS :: MacOS X
Classifier: Operating System :: POSIX
Classifier: Operating System :: Unix
Classifier: Programming Language :: Python
Classifier: Programming Language :: JavaScript
Classifier: Topic :: Scientific/Engineering
Classifier: Topic :: Scientific/Engineering :: Bio-Informatics
Classifier: Topic :: Scientific/Engineering :: Visualization
Requires-Python: >=3.8
License-File: LICENSE
Requires-Dist: boto3
Requires-Dist: click
Requires-Dist: humanize
Requires-Dist: importlib_metadata
Requires-Dist: jinja2>=3.0.0
Requires-Dist: kaleido==0.2.1
Requires-Dist: markdown
Requires-Dist: numpy
Requires-Dist: packaging
Requires-Dist: requests
Requires-Dist: Pillow>=10
Requires-Dist: plotly>=5.18
Requires-Dist: pyyaml>=4
Requires-Dist: rich>=10
Requires-Dist: rich-click
Requires-Dist: coloredlogs
Requires-Dist: spectra>=0.0.10
Requires-Dist: pydantic>=2.7.0
Requires-Dist: typeguard
Requires-Dist: tqdm
Requires-Dist: python-dotenv
Requires-Dist: natsort
Requires-Dist: tiktoken
Requires-Dist: jsonschema
Requires-Dist: polars-lts-cpu
Requires-Dist: pyarrow
Provides-Extra: dev
Requires-Dist: pre-commit; extra == "dev"
Requires-Dist: ruff>=0.8.3; extra == "dev"
Requires-Dist: pdoc3; extra == "dev"
Requires-Dist: pytest; extra == "dev"
Requires-Dist: pytest-cov; extra == "dev"
Requires-Dist: pytest-xdist; extra == "dev"
Requires-Dist: syrupy; extra == "dev"
Requires-Dist: pygithub; extra == "dev"
Requires-Dist: mypy; extra == "dev"
Requires-Dist: types-PyYAML; extra == "dev"
Requires-Dist: types-tqdm; extra == "dev"
Requires-Dist: types-requests; extra == "dev"
Requires-Dist: types-Markdown; extra == "dev"
Requires-Dist: types-beautifulsoup4; extra == "dev"
Requires-Dist: types-Pillow; extra == "dev"
Requires-Dist: types-jsonschema; extra == "dev"
Requires-Dist: types-boto3; extra == "dev"
Requires-Dist: beautifulsoup4; extra == "dev"
Requires-Dist: jupyter; extra == "dev"
